GPUBSMAligner.py
GPUBSMBuilder.py
LICENSE-agpl-3.0.txt
MANIFEST.in
Manual.pdf
merge-sam.sh
setup.py
utilities.py
GPU_BSM.egg-info/PKG-INFO
GPU_BSM.egg-info/SOURCES.txt
GPU_BSM.egg-info/dependency_links.txt
GPU_BSM.egg-info/entry_points.txt
GPU_BSM.egg-info/requires.txt
GPU_BSM.egg-info/top_level.txt
dist/GPU_BSM-2.7.1.2-py2.7.egg
utils/merge-sam.sh
utils/merge-succinct.sh