Metadata-Version: 1.0
Name: GPU-BSM
Version: 2.7.1.2
Summary: A GPU-based Tool to Map Bisulfite-Threated Reads
Home-page: http://www.itb.cnr.it/web/bioinformatics/gpu-bsm
Author: Andrea Manconi
Author-email: andrea.manconi@itb.cnr.it
License: LICENSE-agpl-3.0.txt
Platform: UNKNOWN
